super8/__init__.py
super8/__main__.py
super8/main.py
super8/utils.py
super8-1.0.1.dist-info/METADATA
super8-1.0.1.dist-info/WHEEL
super8-1.0.1.dist-info/entry_points.txt
super8-1.0.1.dist-info/top_level.txt
super8-1.0.1.dist-info/RECORD
