Metadata-Version: 2.1
Name: super8
Version: 1.0.1
Summary: open-source toolset for video analysis
Home-page: https://github.com/blancai/super8
Author: Rich Pavlovskiy
Author-email: rich.pavlovskiy@gmail.com
License: MIT
Platform: UNKNOWN
Classifier: License :: OSI Approved :: MIT License
Classifier: Programming Language :: Python :: 3
Classifier: Programming Language :: Python :: 3.7
